barnone/__init__.py
barnone/colored_progress_bar.py
barnone/progress_bar.py
barnone/utilities.py
barnone-1.0.0.dist-info/licenses/LICENSE
barnone-1.0.0.dist-info/METADATA
barnone-1.0.0.dist-info/WHEEL
barnone-1.0.0.dist-info/top_level.txt
barnone-1.0.0.dist-info/RECORD
