Metadata-Version: 2.4
Name: barnone
Version: 1.0.0
Summary: A lightweight, eye-friendly, and feature-rich terminal progress bar.
Author-email: Nick Stuer <nickstuer@duck.com>
Project-URL: Homepage, https://github.com/nickstuer/barnone
Project-URL: Issues, https://github.com/nickstuer/barnone/issues
Classifier: Development Status :: 5 - Production/Stable
Classifier: Programming Language :: Python :: 3
Classifier: License :: OSI Approved :: MIT License
Classifier: Operating System :: OS Independent
Requires-Python: >=3.9
License-File: LICENSE
Dynamic: license-file
